{
    "VTX": {
        "fre72": "presets/vtx/foxeer/reaper_extreme_v2.txt",
        "fre40": "presets/vtx/foxeer/reaper_extreme_v1.txt",
        "fri40": "presets/vtx/foxeer/reaper_infinity.txt",
        "rms48": "presets/vtx/rushfpv/max_solo.txt",
        "rts48": "presets/vtx/rushfpv/tank_solo.txt",
        "lts48": "presets/vtx/readytosky/lts.txt",
        "afd40": "presets/vtx/akk/fx2_dominator.txt",
        "aul40": "presets/vtx/akk/ultra_long_range.txt",
        "gmp72": "presets/vtx/geprc/maten_pro_v2.txt",
        "gmp40": "presets/vtx/geprc/maten_pro_v1.txt",
        "blw40": "presets/vtx/blitz/whoop.txt"
    }
}